microbmp/__init__.py
microbmp-0.2.0.dist-info/LICENSE
microbmp-0.2.0.dist-info/METADATA
microbmp-0.2.0.dist-info/WHEEL
microbmp-0.2.0.dist-info/top_level.txt
microbmp-0.2.0.dist-info/RECORD
